README.txt
setup.py
iqpp/__init__.py
iqpp.plone.rotating.egg-info/PKG-INFO
iqpp.plone.rotating.egg-info/SOURCES.txt
iqpp.plone.rotating.egg-info/dependency_links.txt
iqpp.plone.rotating.egg-info/entry_points.txt
iqpp.plone.rotating.egg-info/namespace_packages.txt
iqpp.plone.rotating.egg-info/not-zip-safe
iqpp.plone.rotating.egg-info/requires.txt
iqpp.plone.rotating.egg-info/top_level.txt
iqpp/plone/__init__.py
iqpp/plone/rotating/__init__.py
iqpp/plone/rotating/config.py
iqpp/plone/rotating/configure.zcml
iqpp/plone/rotating/interfaces.py
iqpp/plone/rotating/profiles.zcml
iqpp/plone/rotating/adapters/__init__.py
iqpp/plone/rotating/adapters/configure.zcml
iqpp/plone/rotating/adapters/data.py
iqpp/plone/rotating/adapters/options.py
iqpp/plone/rotating/adapters/rotating.py
iqpp/plone/rotating/browser/__init__.py
iqpp/plone/rotating/browser/configure.zcml
iqpp/plone/rotating/browser/options.pt
iqpp/plone/rotating/browser/options.py
iqpp/plone/rotating/portlets/__init__.py
iqpp/plone/rotating/portlets/configure.zcml
iqpp/plone/rotating/portlets/rotating.pt
iqpp/plone/rotating/portlets/rotating.py
iqpp/plone/rotating/profiles/default/actions.xml
iqpp/plone/rotating/profiles/default/catalog.xml
iqpp/plone/rotating/profiles/default/portlets.xml
iqpp/plone/rotating/tests/__init__.py
iqpp/plone/rotating/tests/base.py
iqpp/plone/rotating/tests/test_rotating.py