Metadata-Version: 1.0
Name: iqpp.plone.rotating
Version: 0.1b1
Summary: Rotating content for Plone
Home-page: http://www.iqpp.de
Author: Kai Diefenbach
Author-email: kai.diefenbach@iqpp.de
License: GPL
Download-URL: http://cheeseshop.python.org/pypi/iqpp.plone.rotating/
Keywords: plone rotating random
Platform: UNKNOWN
Classifier: Framework :: Plone
Classifier: Framework :: Zope2
Classifier: Framework :: Zope3
Classifier: Programming Language :: Python
Classifier: Topic :: Software Development :: Libraries :: Python Modules
